panel_bootstrap_vue/__init__.py
panel_bootstrap_vue/page.py
panel_bootstrap_vue/www/bootstrap/bootstrap.min.css
panel_bootstrap_vue/www/typography/core.css
panel_bootstrap_vue/www/typography/core.min.css
panel_bootstrap_vue/www/typography/fonts/adobe-source-sans-pro/6xK1dSBYKcSV-LCoeQqfX1RYOo3qPZ7nsDQ.woff
panel_bootstrap_vue/www/typography/fonts/adobe-source-sans-pro/6xK3dSBYKcSV-LCoeQqfX1RYOo3qOK7j.woff
panel_bootstrap_vue/www/typography/fonts/adobe-source-sans-pro/6xKydSBYKcSV-LCoeQqfX1RYOo3ig4vwlxdo.woff
panel_bootstrap_vue/www/typography/fonts/adobe-source-sans-pro/6xKydSBYKcSV-LCoeQqfX1RYOo3ik4zwlxdo.woff
panel_bootstrap_vue/www/typography/fonts/font-awesome/fa-brands-400.woff
panel_bootstrap_vue/www/typography/fonts/font-awesome/fa-regular-400.woff
panel_bootstrap_vue/www/typography/fonts/font-awesome/fa-solid-900.woff
panel_bootstrap_vue/www/typography/fonts/unicode_literals.py
panel_bootstrap_vue/www/typography/fonts/uri_font.py
panel_bootstrap_vue/www/vue/bootstrap-vue-icons.min.js
panel_bootstrap_vue/www/vue/bootstrap-vue.min.css
panel_bootstrap_vue/www/vue/bootstrap-vue.min.js
panel_bootstrap_vue/www/vue/portal-vue.umd.min.js
panel_bootstrap_vue-0.1.2.dist-info/LICENSE
panel_bootstrap_vue-0.1.2.dist-info/WHEEL
panel_bootstrap_vue-0.1.2.dist-info/METADATA
panel_bootstrap_vue-0.1.2.dist-info/RECORD
